{
  "alerts": {
    "m24:RETARD:d": 1784135785063,
    "m24:BINANCIAN:d": 1784225157765,
    "m24:TCC:d": 1784243517863,
    "m24:CHANCE:u": 1784268129255,
    "m24:CZ:d": 1784268129691,
    "m1h:TCC:u": 1784085797217,
    "m24:TCC:u": 1784147978096,
    "m1h:CZ:u": 1784119364711,
    "m24:CZ:u": 1784163721690,
    "m1h:BINANCIAN:u": 1784051688132,
    "m24:ANSEM:d": 1784247161920,
    "m24:BINANCIAN:u": 1784073914543,
    "macdsig:SOLUSDT:1783854000000": 1783857750869,
    "m1h:CHANCE:d": 1784135784954,
    "m1h:TCC:d": 1783864153490,
    "m1h:HEDGE:u": 1784243518192,
    "m24:HEDGE:d": 1784211806438,
    "macdsig:XRPUSDT:1783861200000": 1783867424220,
    "macdsig:XLMUSDT:1783861200000": 1783867424448,
    "macdsig:DOGEUSDT:1783861200000": 1783867424676,
    "hilosig:ETHUSDT:1783864800000": 1783870905255,
    "m1h:BINANCIAN:d": 1784038448985,
    "hilosig:XLMUSDT:1783868400000": 1783874115703,
    "m1h:HEDGE:d": 1784247162158,
    "m1h:RETARD:u": 1784151320160,
    "m24:RETARD:u": 1784211805863,
    "hilosig:BTCUSDT:1783882800000": 1783888046620,
    "hilosig:SOLUSDT:1783882800000": 1783888047175,
    "m1h:CHANCE:u": 1784221161353,
    "m1h:RETARD:d": 1783888048150,
    "hilosig:BTCUSDT:1783890000000": 1783894068485,
    "hilosig:SOLUSDT:1783890000000": 1783894069086,
    "hilosig:XLMUSDT:1783890000000": 1783894069687,
    "macdsig:ETHUSDT:1783893600000": 1783897438595,
    "hilosig:ETHUSDT:1783893600000": 1783897438595,
    "m24:ANSEM:u": 1784283291193,
    "rsi:BTCUSDT:low": 1784268128092,
    "m24:HEDGE:u": 1784276644166,
    "macdsig:XLMUSDT:1783951200000": 1783956507292,
    "macdsig:DOGEUSDT:1783951200000": 1783956507591,
    "rsi:XRPUSDT:low": 1783968904249,
    "rsi:DOGEUSDT:low": 1783968904848,
    "m1h:CZ:d": 1784283291285,
    "m24:CHANCE:d": 1784199045450,
    "m1h:ANSEM:u": 1784217140097,
    "conv:2n7dcVzeKi3z7PyU7iu5dL4GboHjZjQ7TdtdRVtwpump:2": 1784021054605,
    "hilosig:ETHUSDT:1784023200000": 1784026808452,
    "macdsig:XLMUSDT:1784023200000": 1784026809280,
    "hilosig:BTCUSDT:1784026800000": 1784031199835,
    "move:ETHUSDT:up": 1784107906694,
    "rsi:ETHUSDT:high": 1784125645809,
    "rsi:XRPUSDT:high": 1784125646361,
    "rsi:DOGEUSDT:high": 1784038448809,
    "conv:FLKqVhmeDqwiwSmWZgQhFGn6ish1BM3zksfyKwBrpump:3": 1784038450318,
    "rsi:BTCUSDT:high": 1784043944461,
    "conv:4YpANZ4urF4DW2QtCMP54kZQkhsisypsstJbasQapump:3": 1784043948601,
    "conv:GCvWyFFgcuGoeXqskkpGjZs2onoApbbhkoDHui1Cpump:4": 1784047946766,
    "conv:GCvWyFFgcuGoeXqskkpGjZs2onoApbbhkoDHui1Cpump:2": 1784051689488,
    "conv:31mMFCFe3V5tx319s5kNfnPrYCzc8SuxPofGcyfepump:3": 1784055438133,
    "conv:EXTvbbAKdhASAazTfDmR1FhwFeQBrbz1uqcxFk6E1jAF:4": 1784059567048,
    "conv:Z4S3sHmJmcY44oBNFA4sJtM5Ks2dfSnniGQwi4GaX5v:3": 1784059567048,
    "conv:5LfjZQ4nbx2Kkodksdr7e4tTZKhB3Tqk6bDQ43nGUNna:2": 1784059567048,
    "conv:2RfXjaiepngcBuGgPLtdnH22g68eetpgzCDX44Hnpump:3": 1784063420492,
    "conv:8y8K7tR7G2WgYydqCyVfsNpHQ2pJ4B3e8ANXCtf5pump:3": 1784063420492,
    "conv:2PrJoPoRzsm8DNuH6XPcTCtvt8XFzHBxqjwG5UC1pump:4": 1784067170007,
    "conv:B887p4K81vnF9ar13TB4gdAgjPRJXL77ztvXyjsypump:3": 1784067170007,
    "conv:EPVXXm1NH7z9pxtuRff3LHt8bkY8Ui4BXT5eVTUS7EA3:3": 1784070680185,
    "rsi:SOLUSDT:high": 1784073913334,
    "macdsig:XLMUSDT:1784080800000": 1784085796706,
    "conv:3hqrigP7PiomQQ5RtdYE9kagmo2q4r3euae2fEJWpump:2": 1784085798966,
    "conv:EPVXXm1NH7z9pxtuRff3LHt8bkY8Ui4BXT5eVTUS7EA3:2": 1784085798966,
    "conv:CT9R58XWLT2KytvWMfkH4reLA8avFqm7rNJ6LAyDpump:2": 1784085798966,
    "conv:4xjs9YJD8RgTdm1iTSqt7yEznoaCTB4kKNSco3z7pump:3": 1784094271247,
    "macdsig:DOGEUSDT:1784131200000": 1784135784713,
    "mliq:HEDGE": 1784135785466,
    "m1h:ANSEM:d": 1784139611778,
    "conv:CuHF7DByaLxkaf7Wrnx5CwUJwuuNNfvsmzdhns62pump:2": 1784243521430,
    "macdsig:XRPUSDT:1784138400000": 1784144399549,
    "conv:GqQc4tjs6RkZt1EdsehKLZvNDTpZc9n3UHGxnbfNpump:2": 1784154821408,
    "hilosig:BTCUSDT:1784160000000": 1784163719664,
    "hilosig:SOLUSDT:1784160000000": 1784163720342,
    "hilosig:DOGEUSDT:1784160000000": 1784163721355,
    "macdsig:XLMUSDT:1784170800000": 1784175448446,
    "hilosig:XRPUSDT:1784185200000": 1784192219404,
    "conv:CtY9Uv4Tuv7jwoAPt9iHhFxn9GK6F1gRj3CvPMospump:4": 1784192222697,
    "conv:AaeRR63ihifBE6h9TVH9LV8tnN6u68ewHXHrJoRP5DZJ:2": 1784225159958,
    "macdsig:XLMUSDT:1784224800000": 1784229931690,
    "hilosig:XLMUSDT:1784242800000": 1784247161388,
    "rsi:ETHUSDT:low": 1784259443844,
    "move:ETHUSDT:down": 1784268128202,
    "rsi:SOLUSDT:low": 1784268128538
  },
  "rsiZone": {
    "BTCUSDT": "mid",
    "ETHUSDT": "mid",
    "SOLUSDT": "mid",
    "XRPUSDT": "mid",
    "XLMUSDT": "mid",
    "DOGEUSDT": "mid"
  },
  "sigSeen": {
    "macd:SOLUSDT": 1783854000000,
    "macd:XRPUSDT": 1784138400000,
    "macd:XLMUSDT": 1784224800000,
    "macd:DOGEUSDT": 1784131200000,
    "hilo:ETHUSDT": 1784023200000,
    "hilo:XLMUSDT": 1784242800000,
    "hilo:BTCUSDT": 1784160000000,
    "hilo:SOLUSDT": 1784160000000,
    "macd:ETHUSDT": 1783893600000,
    "hilo:DOGEUSDT": 1784160000000,
    "hilo:XRPUSDT": 1784185200000
  },
  "siteDown": false,
  "wallSig": {
    "Bi4rd5FH5bYEN8scZ7wevxNZyNmKHdaBcvewdPFxYdLt": "2sDoTMXjnv4c877MdjNSVCDnL844SFRrJZoVxToz1iPtrKJfq27LEUwVQcd3j7HWnnBS7AzBMEVJR38BQUAsyJNi",
    "5ZuV8eqkvzYFVEKbLvGBdexL2tFv7E5BCd2HZpjqbdg": "n1bM86ss6nYAU1EHRcPYgF1154NjA9uB1b8KR3SZUkcGfdkyxNC4F94YiGro5N6jPxnTSAnwbBECdS5nXLmpNAL",
    "DAEdBmTPEKM6xkwfzC3d411QUe6coKpkND6UURa4CvHC": "4keqSpNyH7soFfsnFEyw9qoVc4y6ydDnDADi1QCGKAM5HUWGvMzQMpwLmLB459p2sVUe2cQwii2dzwYAmus9BkS4",
    "DjM7Tu7whh6P3pGVBfDzwXAx2zaw51GJWrJE3PwtuN7s": "2juPj4aGpaLDPSQ9ZFM4Kpg1wyBFkgW8zx51tvDACTHXGsxh1B9yqbpw7CTAMb1gagAYuDM3iV5j1p9PUAj5oDTC",
    "78N177fzNJpp8pG49xDv1efYcTMSzo9tPTKEA9mAVkh2": "3zqo6dsWxoxV6q3wci48hgbeH2TTmLubjWbHaoUU2ZsEG7HKMJAzECKvmrHwjTEYHJB2gmZLEVgY4akNa8JMgBwe",
    "J6TDXvarvpBdPXTaTU8eJbtso1PUCYKGkVtMKUUY8iEa": "2bMUrQNnXKKC6LRLFxt75BkKowTat4bSJYUgDj9tGZPWVSWoMe87hc1zaG3yRyzbjaRpsG2qwsZZtduKyxx8St7C",
    "D1H83ueSw5Nxy5okxH7VBfV4jRnqAK5Mm1tm3JAj3m5t": "ne2VzN7ZcAAYZuLeJAbC8cxX94hzUdo19QnJ7SRwwLy8LcsXE3iwgo2eKnYK7EQQoDszxkopjAWpgXs1Dn1nEYC",
    "831yhv67QpKqLBJjbmw2xoDUeeFHGUx8RnuRj9imeoEs": "4gCz9JKhhFfdkDvoNjdi8LbD9Bkk3HcExLpdPqj7QeNuT8N2stB5Bz2uKAqjm85vYwYwvoZ265rUQHjshBbYHLvr",
    "H31vEBxSJk1nQdUN11qZgZyhScyShhscKhvhZZU3dQoU": "4do4wguMpGSTALbQqjs9cG9HhgMW2r7XcQnookZnMxtMjtmvLvXZr913YwsbxZTq67h6twd8T79ST6fyda1DjJqu",
    "3uz65G8e463MA5FxcSu1rTUyWRtrRLRZYskKtEHHj7qn": "2SAGkZBcCVwjWoVSUmpK1ci8y4XGUPZgfnDvscF9fy7iMextRguPgj7ePXeBTb5PWa9jJeM3PKETu3zobQfAgvVN"
  },
  "buys": [
    {
      "mint": "GqQc4tjs6RkZt1EdsehKLZvNDTpZc9n3UHGxnbfNpump",
      "sym": "$BARRON",
      "name": "Doji #2",
      "ts": 1784199046164,
      "usd": 16.539689229066383,
      "liq": 43007.91
    },
    {
      "mint": "9e21XRWPrybZm4oLzGFkhcNcdNJhHtdo8VR9V2nCpump",
      "sym": "$BigEd",
      "name": "Felix #10",
      "ts": 1784199046651,
      "usd": 43.73006923883642,
      "liq": 0
    },
    {
      "mint": "DTCNpKqec2RN3ptE9H863gWC4QTk1uXZf1b6jGTjpump",
      "sym": "$PUPWIF",
      "name": "Fox #3",
      "ts": 1784203973602,
      "usd": 0.11645,
      "liq": 0
    },
    {
      "mint": "9cRCn9rGT8V2imeM2BaKs13yhMEais3ruM3rPvTGpump",
      "sym": "$ANSEM",
      "name": "Fox #3",
      "ts": 1784203973662,
      "usd": 0.0038739115993026646,
      "liq": 1881039.52
    },
    {
      "mint": "GaZb3DE2U3Jcjx7ddAVwobsBKnCaDoJWLbzTvJYhpump",
      "sym": "$ANSUM",
      "name": "Fox #3",
      "ts": 1784203973715,
      "usd": 0.09206262125999959,
      "liq": 39456.33
    },
    {
      "mint": "F3Y4w4UKVEY1Zzj1Vjk2c3DwtaMG4uvd9uuwgnL8pump",
      "sym": "$CASHBULL",
      "name": "Fox #3",
      "ts": 1784211807514,
      "usd": 0.3263,
      "liq": 4323.94
    },
    {
      "mint": "vp1zibJ5obZLopoEy838WrEqHxTKm2suc37yxV4gnA4",
      "sym": "$A4",
      "name": "Pain #6",
      "ts": 1784211808690,
      "usd": 111.840795247114,
      "liq": 0
    },
    {
      "mint": "vp1zibJ5obZLopoEy838WrEqHxTKm2suc37yxV4gnA4",
      "sym": "$A4",
      "name": "Pain #6",
      "ts": 1784211808858,
      "usd": 8.111350461825033,
      "liq": 0
    },
    {
      "mint": "BgVMUdzzKUAgjrKmLTT9aKXJUoew9YAqHrJUfs7xpump",
      "sym": "$Peigengoo",
      "name": "Sheep #5",
      "ts": 1784217140739,
      "usd": 0.9260897345426978,
      "liq": 18469.78
    },
    {
      "mint": "BgVMUdzzKUAgjrKmLTT9aKXJUoew9YAqHrJUfs7xpump",
      "sym": "$Peigengoo",
      "name": "Sheep #5",
      "ts": 1784217140841,
      "usd": 0.9259214124683695,
      "liq": 18469.78
    },
    {
      "mint": "BgVMUdzzKUAgjrKmLTT9aKXJUoew9YAqHrJUfs7xpump",
      "sym": "$Peigengoo",
      "name": "Sheep #5",
      "ts": 1784217140877,
      "usd": 0.9257531362707713,
      "liq": 18469.78
    },
    {
      "mint": "Ge87EtsjwRQbHaqQmKRno69RFTwh9bfSsm99XNxTpump",
      "sym": "$Jimothy",
      "name": "Pain #6",
      "ts": 1784217140993,
      "usd": 175.54021586555638,
      "liq": 20044.98
    },
    {
      "mint": "3Tf3RD5t45wQJF8uEYVXpR2M4wBiCaSNwUWENzVGpump",
      "sym": "$Meowpin",
      "name": "Pain #6",
      "ts": 1784217141057,
      "usd": 1025.8476251556003,
      "liq": 46885.77
    },
    {
      "mint": "3EvaEZNK19WVadiTzNicy1aYHF6VCNWVEERvS42vMoon",
      "sym": "$GCAT",
      "name": "Megga #9",
      "ts": 1784217141207,
      "usd": 188.41361335604878,
      "liq": 0
    },
    {
      "mint": "Fzh9yPtEina2UKGw4Z749m3sv96Z8sZFWC8ip344pioE",
      "sym": "$Turtle",
      "name": "Felix #10",
      "ts": 1784217141762,
      "usd": 267.69594170138566,
      "liq": 0
    },
    {
      "mint": "9cRCn9rGT8V2imeM2BaKs13yhMEais3ruM3rPvTGpump",
      "sym": "$ANSEM",
      "name": "Fox #3",
      "ts": 1784221161820,
      "usd": 0.002026059991144575,
      "liq": 2016101.3
    },
    {
      "mint": "GaZb3DE2U3Jcjx7ddAVwobsBKnCaDoJWLbzTvJYhpump",
      "sym": "$ANSUM",
      "name": "Fox #3",
      "ts": 1784221161861,
      "usd": 0.043041554595901824,
      "liq": 38583.34
    },
    {
      "mint": "Ge87EtsjwRQbHaqQmKRno69RFTwh9bfSsm99XNxTpump",
      "sym": "$Jimothy",
      "name": "Pain #6",
      "ts": 1784221162156,
      "usd": 114.05601422233342,
      "liq": 22527.59
    },
    {
      "mint": "GoFJ78jZsPhk3i5dyy8tmbpf4c6RkvRD6Vw3sUPfpump",
      "sym": "$Earl",
      "name": "Megga #9",
      "ts": 1784221162283,
      "usd": 318.04147172738675,
      "liq": 12836.41
    },
    {
      "mint": "AaeRR63ihifBE6h9TVH9LV8tnN6u68ewHXHrJoRP5DZJ",
      "sym": "$GHOSTI",
      "name": "Doji #2",
      "ts": 1784225158264,
      "usd": 174.9320419270499,
      "liq": 46178.5
    },
    {
      "mint": "AaeRR63ihifBE6h9TVH9LV8tnN6u68ewHXHrJoRP5DZJ",
      "sym": "$GHOSTI",
      "name": "Doji #2",
      "ts": 1784225158336,
      "usd": 182.98509576304855,
      "liq": 46178.5
    },
    {
      "mint": "AaeRR63ihifBE6h9TVH9LV8tnN6u68ewHXHrJoRP5DZJ",
      "sym": "$GHOSTI",
      "name": "Doji #2",
      "ts": 1784225158433,
      "usd": 263.4997006776284,
      "liq": 46178.5
    },
    {
      "mint": "7NmbCaQpjpTcze5bmvWWJPjiaXMjHnLNYj9vJBG5pump",
      "sym": "$BOBAOPPA",
      "name": "Pain #6",
      "ts": 1784225159121,
      "usd": 506.57423824415605,
      "liq": 57193.82
    },
    {
      "mint": "7NmbCaQpjpTcze5bmvWWJPjiaXMjHnLNYj9vJBG5pump",
      "sym": "$BOBAOPPA",
      "name": "Pain #6",
      "ts": 1784225159240,
      "usd": 936.7494431063682,
      "liq": 57193.82
    },
    {
      "mint": "7NmbCaQpjpTcze5bmvWWJPjiaXMjHnLNYj9vJBG5pump",
      "sym": "$BOBAOPPA",
      "name": "Pain #6",
      "ts": 1784225159377,
      "usd": 782.7177646186738,
      "liq": 57193.82
    },
    {
      "mint": "AaeRR63ihifBE6h9TVH9LV8tnN6u68ewHXHrJoRP5DZJ",
      "sym": "$GHOSTI",
      "name": "Megga #9",
      "ts": 1784225159799,
      "usd": 83.84863775782858,
      "liq": 46178.5
    },
    {
      "mint": "AaeRR63ihifBE6h9TVH9LV8tnN6u68ewHXHrJoRP5DZJ",
      "sym": "$GHOSTI",
      "name": "Megga #9",
      "ts": 1784225159902,
      "usd": 83.74238421992102,
      "liq": 46178.5
    },
    {
      "mint": "3kepG3Gq7RHQNm97Tk2jKWXkSU8QMFK9t7h5kTedpump",
      "sym": "$ㅤㅤㅤ",
      "name": "Fox #3",
      "ts": 1784229932668,
      "usd": 166.6699045854926,
      "liq": 6113.96
    },
    {
      "mint": "7NmbCaQpjpTcze5bmvWWJPjiaXMjHnLNYj9vJBG5pump",
      "sym": "$BOBAOPPA",
      "name": "Pain #6",
      "ts": 1784229932893,
      "usd": 725.0655879577416,
      "liq": 69459.98
    },
    {
      "mint": "7NmbCaQpjpTcze5bmvWWJPjiaXMjHnLNYj9vJBG5pump",
      "sym": "$BOBAOPPA",
      "name": "Pain #6",
      "ts": 1784229932951,
      "usd": 105.79393114999647,
      "liq": 69459.98
    },
    {
      "mint": "Ge87EtsjwRQbHaqQmKRno69RFTwh9bfSsm99XNxTpump",
      "sym": "$Jimothy",
      "name": "Pain #6",
      "ts": 1784229933203,
      "usd": 104.88467695648643,
      "liq": 32150.26
    },
    {
      "mint": "6AVAUKa9uxQpruHZUinFECpXEh1usRVtzQWK8N2wpump",
      "sym": "$SCAM",
      "name": "Jeets #7",
      "ts": 1784229933346,
      "usd": 19.65565991841604,
      "liq": 108732.83
    },
    {
      "mint": "6AVAUKa9uxQpruHZUinFECpXEh1usRVtzQWK8N2wpump",
      "sym": "$SCAM",
      "name": "Jeets #7",
      "ts": 1784229933395,
      "usd": 19.61467340750585,
      "liq": 108732.83
    },
    {
      "mint": "YSBFBBuusbno8ZsFZVzpPZ1FVVhmvGg58yU8LXSpump",
      "sym": "$RWA",
      "name": "Megga #9",
      "ts": 1784229933520,
      "usd": 207.35757282014188,
      "liq": 0
    },
    {
      "mint": "GqQc4tjs6RkZt1EdsehKLZvNDTpZc9n3UHGxnbfNpump",
      "sym": "$BARRON",
      "name": "Doji #2",
      "ts": 1784232969107,
      "usd": 37.668567688126494,
      "liq": 32275.78
    },
    {
      "mint": "9cRCn9rGT8V2imeM2BaKs13yhMEais3ruM3rPvTGpump",
      "sym": "$ANSEM",
      "name": "Fox #3",
      "ts": 1784232969272,
      "usd": 0.004540081503312103,
      "liq": 2077548.59
    },
    {
      "mint": "GaZb3DE2U3Jcjx7ddAVwobsBKnCaDoJWLbzTvJYhpump",
      "sym": "$ANSUM",
      "name": "Fox #3",
      "ts": 1784232969328,
      "usd": 0.09876604517999853,
      "liq": 41329.22
    },
    {
      "mint": "BaXX9FXAktUc6wb9ktvSRR2uwQW3zG9QqMVnbo6pump",
      "sym": "$Sol",
      "name": "Megga #9",
      "ts": 1784232969805,
      "usd": 230.25048420535612,
      "liq": 8765.02
    },
    {
      "mint": "BaXX9FXAktUc6wb9ktvSRR2uwQW3zG9QqMVnbo6pump",
      "sym": "$Sol",
      "name": "Megga #9",
      "ts": 1784232969860,
      "usd": 75.47724738698186,
      "liq": 8765.02
    },
    {
      "mint": "CNmP27kRTL6rA28pyytVw56dtWSQ9MHD1kYbNT9Spump",
      "sym": "$YEET",
      "name": "Sheep #5",
      "ts": 1784236634284,
      "usd": 0.023045469120550003,
      "liq": 0
    },
    {
      "mint": "CHYpWuxTFrnYny2afi4Ruey9c8cE7RkakdhQArY9pump",
      "sym": "$JSON",
      "name": "Sheep #5",
      "ts": 1784236634383,
      "usd": 0.012260418395579998,
      "liq": 0
    },
    {
      "mint": "Hh3oTaqDCKKfdBgsQEvxp9sUwyNf8x9qmKqEMLBWpump",
      "sym": "$HODL",
      "name": "Pain #6",
      "ts": 1784236634531,
      "usd": 49.154987958581586,
      "liq": 123484.64
    },
    {
      "mint": "7NmbCaQpjpTcze5bmvWWJPjiaXMjHnLNYj9vJBG5pump",
      "sym": "$BOBAOPPA",
      "name": "Pain #6",
      "ts": 1784236634595,
      "usd": 143.1448936702884,
      "liq": 73368.49
    },
    {
      "mint": "BuSGZ4eHDHs3HJdW9RrWRk1JEx5o4mr94s1XiZehpump",
      "sym": "$spaceballs",
      "name": "Megga #9",
      "ts": 1784236634837,
      "usd": 67.41749696605422,
      "liq": 0
    },
    {
      "mint": "BgVMUdzzKUAgjrKmLTT9aKXJUoew9YAqHrJUfs7xpump",
      "sym": "$Peigengoo",
      "name": "Sheep #5",
      "ts": 1784240207214,
      "usd": 0.7520051105180657,
      "liq": 17134.58
    },
    {
      "mint": "BgVMUdzzKUAgjrKmLTT9aKXJUoew9YAqHrJUfs7xpump",
      "sym": "$Peigengoo",
      "name": "Sheep #5",
      "ts": 1784240207494,
      "usd": 0.751873124734596,
      "liq": 17134.58
    },
    {
      "mint": "BgVMUdzzKUAgjrKmLTT9aKXJUoew9YAqHrJUfs7xpump",
      "sym": "$Peigengoo",
      "name": "Sheep #5",
      "ts": 1784240207609,
      "usd": 0.7517411736632965,
      "liq": 17134.58
    },
    {
      "mint": "A9fxKGMGgU7oBM4dWkKDMCDcVjomY9XcHAPg4oPHpump",
      "sym": "$ronnie",
      "name": "Megga #9",
      "ts": 1784240209115,
      "usd": 66.29693963258445,
      "liq": 0
    },
    {
      "mint": "4D3pBrESZfrAJvRLh41og7HDUZ2ueYL7sFkt5m9opump",
      "sym": "$Fugazi",
      "name": "Doji #2",
      "ts": 1784243518534,
      "usd": 4.81945204879188,
      "liq": 0
    },
    {
      "mint": "CuHF7DByaLxkaf7Wrnx5CwUJwuuNNfvsmzdhns62pump",
      "sym": "$ALIEN",
      "name": "Doji #2",
      "ts": 1784243518781,
      "usd": 0.000006013097387,
      "liq": 4391.42
    },
    {
      "mint": "CuHF7DByaLxkaf7Wrnx5CwUJwuuNNfvsmzdhns62pump",
      "sym": "$ALIEN",
      "name": "LUKEY #4",
      "ts": 1784243519219,
      "usd": 0.000006013097387000002,
      "liq": 4391.42
    },
    {
      "mint": "CuHF7DByaLxkaf7Wrnx5CwUJwuuNNfvsmzdhns62pump",
      "sym": "$ALIEN",
      "name": "LUKEY #4",
      "ts": 1784243519332,
      "usd": 0.000006013097386999995,
      "liq": 4391.42
    },
    {
      "mint": "CuHF7DByaLxkaf7Wrnx5CwUJwuuNNfvsmzdhns62pump",
      "sym": "$ALIEN",
      "name": "LUKEY #4",
      "ts": 1784243519469,
      "usd": 0.000006239457318,
      "liq": 4391.42
    },
    {
      "mint": "ALk3AwXdjFiTBq1KYFbEt9uBQfDwREYEHZQUz3dfpump",
      "sym": "$AI",
      "name": "Sheep #5",
      "ts": 1784243519762,
      "usd": 0.007056467287548,
      "liq": 0
    },
    {
      "mint": "BFbm1jnzGFhaTPD2Y4fRUgsEdkPF8YXPwDpG2JeHpump",
      "sym": "$QUARTER",
      "name": "Sheep #5",
      "ts": 1784243519945,
      "usd": 0.020584433919538996,
      "liq": 0
    },
    {
      "mint": "KLqsazUTwRWECwqJzjMh7ZSYD8rG4voNsESPJCupump",
      "sym": "$Argo",
      "name": "Pain #6",
      "ts": 1784243520226,
      "usd": 2.1078049680770627,
      "liq": 23134.83
    },
    {
      "mint": "KLqsazUTwRWECwqJzjMh7ZSYD8rG4voNsESPJCupump",
      "sym": "$Argo",
      "name": "Pain #6",
      "ts": 1784243520328,
      "usd": 2.105978951676389,
      "liq": 23134.83
    },
    {
      "mint": "Ge87EtsjwRQbHaqQmKRno69RFTwh9bfSsm99XNxTpump",
      "sym": "$Jimothy",
      "name": "Pain #6",
      "ts": 1784243520497,
      "usd": 127.66777482012432,
      "liq": 34621.46
    },
    {
      "mint": "EPjFWdd5AufqSSqeM2qN1xzybapC8G4wEGGkZwyTDt1v",
      "sym": "$USDC",
      "name": "Jeets #7",
      "ts": 1784243520691,
      "usd": 0.0010006299999905579,
      "liq": 3775937.54
    },
    {
      "mint": "EPjFWdd5AufqSSqeM2qN1xzybapC8G4wEGGkZwyTDt1v",
      "sym": "$USDC",
      "name": "Jeets #7",
      "ts": 1784243520791,
      "usd": 0.00010006300000332173,
      "liq": 3775937.54
    },
    {
      "mint": "27FxtBvRMfYqREqSBdf8241uHqxz6LUuUwpXT5VQpump",
      "sym": "$GEEG",
      "name": "Megga #9",
      "ts": 1784243521226,
      "usd": 96.2708990484253,
      "liq": 3395.04
    },
    {
      "mint": "4D3pBrESZfrAJvRLh41og7HDUZ2ueYL7sFkt5m9opump",
      "sym": "$Fugazi",
      "name": "Doji #2",
      "ts": 1784247162826,
      "usd": 3.264018748891903,
      "liq": 0
    },
    {
      "mint": "9cRCn9rGT8V2imeM2BaKs13yhMEais3ruM3rPvTGpump",
      "sym": "$ANSEM",
      "name": "Fox #3",
      "ts": 1784247163189,
      "usd": 0.0009410288077779114,
      "liq": 1848789.49
    },
    {
      "mint": "AnzkqqNYoa4DnAP21z257PTcgVgmnS9zmJ8dYKAGpump",
      "sym": "$Elgatito",
      "name": "Sheep #5",
      "ts": 1784247163544,
      "usd": 0.018523872489148,
      "liq": 0
    },
    {
      "mint": "KLqsazUTwRWECwqJzjMh7ZSYD8rG4voNsESPJCupump",
      "sym": "$Argo",
      "name": "Pain #6",
      "ts": 1784247163762,
      "usd": 0.04854201151334795,
      "liq": 6415.49
    },
    {
      "mint": "27FxtBvRMfYqREqSBdf8241uHqxz6LUuUwpXT5VQpump",
      "sym": "$GEEG",
      "name": "Megga #9",
      "ts": 1784247164416,
      "usd": 80.98332005551798,
      "liq": 3090.41
    },
    {
      "mint": "4D3pBrESZfrAJvRLh41og7HDUZ2ueYL7sFkt5m9opump",
      "sym": "$Fugazi",
      "name": "Doji #2",
      "ts": 1784259445609,
      "usd": 3.1025314165724933,
      "liq": 12107.4
    },
    {
      "mint": "4D3pBrESZfrAJvRLh41og7HDUZ2ueYL7sFkt5m9opump",
      "sym": "$Fugazi",
      "name": "Doji #2",
      "ts": 1784259445665,
      "usd": 3.07292826494501,
      "liq": 12107.4
    },
    {
      "mint": "9zvmrrakWP9CKBrr2rkv1WQidxjwQezvcTPgKYVupump",
      "sym": "9zvmrr…",
      "name": "LUKEY #4",
      "ts": 1784259446373,
      "usd": 0,
      "liq": 0
    },
    {
      "mint": "zqXWnsxkG1NKa7oCvHLNcpR5Tw17veuAESiHSqfjHha",
      "sym": "$VISTA",
      "name": "Pain #6",
      "ts": 1784259446702,
      "usd": 36.3958567837149,
      "liq": 0
    },
    {
      "mint": "Ge87EtsjwRQbHaqQmKRno69RFTwh9bfSsm99XNxTpump",
      "sym": "$Jimothy",
      "name": "Pain #6",
      "ts": 1784259446884,
      "usd": 179.22991012920923,
      "liq": 52558
    },
    {
      "mint": "4D3pBrESZfrAJvRLh41og7HDUZ2ueYL7sFkt5m9opump",
      "sym": "$Fugazi",
      "name": "Doji #2",
      "ts": 1784268130170,
      "usd": 3.468907537367909,
      "liq": 10996.82
    },
    {
      "mint": "4D3pBrESZfrAJvRLh41og7HDUZ2ueYL7sFkt5m9opump",
      "sym": "$Fugazi",
      "name": "Doji #2",
      "ts": 1784268130445,
      "usd": 3.6733503566419006,
      "liq": 10996.82
    },
    {
      "mint": "BgVMUdzzKUAgjrKmLTT9aKXJUoew9YAqHrJUfs7xpump",
      "sym": "$Peigengoo",
      "name": "Pain #6",
      "ts": 1784268131781,
      "usd": 2.26386625,
      "liq": 16215.43
    },
    {
      "mint": "kPacxo79adsiHijN4qBEaJFjNx7nSBrBUqmngBApump",
      "sym": "$Telvar ",
      "name": "Pain #6",
      "ts": 1784268132249,
      "usd": 0.04269,
      "liq": 1598.03
    },
    {
      "mint": "EPjFWdd5AufqSSqeM2qN1xzybapC8G4wEGGkZwyTDt1v",
      "sym": "$PUMP",
      "name": "Trey #8",
      "ts": 1784268132606,
      "usd": 1.3761499997465876e-7,
      "liq": 13305421.91
    },
    {
      "mint": "4D3pBrESZfrAJvRLh41og7HDUZ2ueYL7sFkt5m9opump",
      "sym": "$Fugazi",
      "name": "Doji #2",
      "ts": 1784276644757,
      "usd": 3.463504549990465,
      "liq": 9674.29
    },
    {
      "mint": "9cRCn9rGT8V2imeM2BaKs13yhMEais3ruM3rPvTGpump",
      "sym": "$ANSEM",
      "name": "Fox #3",
      "ts": 1784276645188,
      "usd": 0.004472949412092567,
      "liq": 2012213.95
    },
    {
      "mint": "GaZb3DE2U3Jcjx7ddAVwobsBKnCaDoJWLbzTvJYhpump",
      "sym": "$ANSUM",
      "name": "Fox #3",
      "ts": 1784276645318,
      "usd": 0.09729122727039945,
      "liq": 43374.74
    },
    {
      "mint": "5rqohXWSYsHha5EtzntRbYa7kMoJ77q3w1mLbke1pump",
      "sym": "$Up",
      "name": "Sheep #5",
      "ts": 1784276645972,
      "usd": 0.024849399841857002,
      "liq": 0
    },
    {
      "mint": "EPjFWdd5AufqSSqeM2qN1xzybapC8G4wEGGkZwyTDt1v",
      "sym": "$PUMP",
      "name": "Trey #8",
      "ts": 1784276646431,
      "usd": 1.4796000009368982e-8,
      "liq": 13409484.47
    },
    {
      "mint": "5FxpQcRrCqYQhbSLXPewDFjAetH8UbDBxVjEfZD5T2mk",
      "sym": "$16",
      "name": "Sheep #5",
      "ts": 1784283291711,
      "usd": 0.1174905011501,
      "liq": 21.13
    },
    {
      "mint": "BhWczVuN1g7HofRgKtQ6zJErhsSV88uxY6Xg996znFoS",
      "sym": "$-‿-",
      "name": "Sheep #5",
      "ts": 1784283291767,
      "usd": 0.08948512093894,
      "liq": 62729.24
    },
    {
      "mint": "kPacxo79adsiHijN4qBEaJFjNx7nSBrBUqmngBApump",
      "sym": "$Telvar ",
      "name": "Pain #6",
      "ts": 1784283291853,
      "usd": 0.04241,
      "liq": 1591.97
    },
    {
      "mint": "BdmmbhuqmMcswTCpP5Dy9H6E87ZqDMULVAWdzu4ZhqTS",
      "sym": "$Quasi",
      "name": "Pain #6",
      "ts": 1784283291923,
      "usd": 279.5786136071739,
      "liq": 0
    }
  ],
  "lastDigest": "2026-07-16"
}